douban2notion/__init__.py
douban2notion/__main__.py
douban2notion/config.py
douban2notion/douban.py
douban2notion/notion_helper.py
douban2notion/update_heatmap.py
douban2notion/utils.py
douban2notion-0.0.13.dist-info/METADATA
douban2notion-0.0.13.dist-info/WHEEL
douban2notion-0.0.13.dist-info/entry_points.txt
douban2notion-0.0.13.dist-info/top_level.txt
douban2notion-0.0.13.dist-info/RECORD
