Metadata-Version: 2.1
Name: douban2notion
Version: 0.0.13
Summary: 自动将豆瓣电影和豆瓣读书同步到Notion
Home-page: https://github.com/malinkang/weread2notion-pro
Author: malinkang
Author-email: linkang.ma@gmail.com
Classifier: Programming Language :: Python :: 3
Classifier: License :: OSI Approved :: MIT License
Classifier: Operating System :: OS Independent
Requires-Python: >=3.6
Requires-Dist: requests
Requires-Dist: pendulum
Requires-Dist: retrying
Requires-Dist: notion-client
Requires-Dist: github-heatmap
Requires-Dist: python-dotenv
Requires-Dist: beautifulsoup4
Requires-Dist: lxml
